jupyterlab_filesystem_access/__init__.py
jupyterlab_filesystem_access/_version.py
jupyterlab_filesystem_access-0.7.0.data/data/share/jupyter/labextensions/jupyterlab-filesystem-access/package.json
jupyterlab_filesystem_access-0.7.0.data/data/share/jupyter/labextensions/jupyterlab-filesystem-access/schemas/jupyterlab-filesystem-access/package.json.orig
jupyterlab_filesystem_access-0.7.0.data/data/share/jupyter/labextensions/jupyterlab-filesystem-access/schemas/jupyterlab-filesystem-access/plugin.json
jupyterlab_filesystem_access-0.7.0.data/data/share/jupyter/labextensions/jupyterlab-filesystem-access/static/611.95a27a2dbe55169bc1e5.js
jupyterlab_filesystem_access-0.7.0.data/data/share/jupyter/labextensions/jupyterlab-filesystem-access/static/747.0bb2cded1867b1473bdd.js
jupyterlab_filesystem_access-0.7.0.data/data/share/jupyter/labextensions/jupyterlab-filesystem-access/static/remoteEntry.1b346271af2ccb850cc1.js
jupyterlab_filesystem_access-0.7.0.data/data/share/jupyter/labextensions/jupyterlab-filesystem-access/static/style.js
jupyterlab_filesystem_access-0.7.0.data/data/share/jupyter/labextensions/jupyterlab-filesystem-access/static/third-party-licenses.json
jupyterlab_filesystem_access-0.7.0.data/data/share/jupyter/labextensions/jupyterlab-filesystem-access/install.json
jupyterlab_filesystem_access-0.7.0.dist-info/METADATA
jupyterlab_filesystem_access-0.7.0.dist-info/WHEEL
jupyterlab_filesystem_access-0.7.0.dist-info/licenses/LICENSE
jupyterlab_filesystem_access-0.7.0.dist-info/RECORD
