Metadata-Version: 2.4
Name: jupyterlab-filesystem-access
Version: 0.7.0
Dynamic: Keywords
Summary: Mount local files using the Filesystem API
Project-URL: Homepage, https://github.com/jupyterlab-contrib/jupyterlab-filesystem-access
Project-URL: Bug Tracker, https://github.com/jupyterlab-contrib/jupyterlab-filesystem-access/issues
Project-URL: Repository, https://github.com/jupyterlab-contrib/jupyterlab-filesystem-access.git
Author: JupyterLab Contrib Team
License: BSD 3-Clause License
License-File: LICENSE
Classifier: Framework :: Jupyter
Classifier: Framework :: Jupyter :: JupyterLab
Classifier: Framework :: Jupyter :: JupyterLab :: 4
Classifier: Framework :: Jupyter :: JupyterLab :: Extensions
Classifier: Framework :: Jupyter :: JupyterLab :: Extensions :: Prebuilt
Classifier: License :: OSI Approved :: BSD License
Classifier: Programming Language :: Python
Classifier: Programming Language :: Python :: 3
Classifier: Programming Language :: Python :: 3.8
Classifier: Programming Language :: Python :: 3.9
Classifier: Programming Language :: Python :: 3.10
Classifier: Programming Language :: Python :: 3.11
Classifier: Programming Language :: Python :: 3.12
Classifier: Programming Language :: Python :: 3.13
Classifier: Programming Language :: Python :: 3.14
Requires-Python: >=3.8
